YoutubeTags/__init__.py
YoutubeTags-1.4.dist-info/LICENSE
YoutubeTags-1.4.dist-info/METADATA
YoutubeTags-1.4.dist-info/WHEEL
YoutubeTags-1.4.dist-info/top_level.txt
YoutubeTags-1.4.dist-info/RECORD
