Metadata-Version: 2.1
Name: YoutubeTags
Version: 1.4
Summary: YoutubeTags is a python third-party api wrapper to Extract Youtube Video Tags without Youtube API
Home-page: https://github.com/nuhmanpk/YoutubeTags
Author: Nuhman Pk
Author-email: nuhmanpk7@gmail.com
License: MIT
Platform: UNKNOWN
Classifier: Programming Language :: Python :: 3
Classifier: License :: OSI Approved :: MIT License
Classifier: Operating System :: OS Independent
Requires-Python: >=3.6
Requires-Dist: bs4
Requires-Dist: requests
